[
  { "id": "manto_t1",    "name": "Manto de Linho Grosseiro",          "emoji": "👘", "type": "armor", "rarity": "common",    "tier": 1,  "description": "Linho grosseiro tecido por artesãos mortais. Proteção mínima.",                            "stats": { "def": 3,    "hp": 22,    "crit": 3    }, "stackable": false },
  { "id": "coura_t1",    "name": "Couraça de Couro Bruto",            "emoji": "🥋", "type": "armor", "rarity": "common",    "tier": 1,  "description": "Couro bruto curtido. Mobilidade básica com proteção modesta.",                             "stats": { "def": 6,    "hp": 10,    "speed": 4   }, "stackable": false },
  { "id": "armadura_t1", "name": "Armadura de Bronze Bruto",          "emoji": "🛡️", "type": "armor", "rarity": "common",    "tier": 1,  "description": "Bronze fundido em placas brutas. Pesada mas protetora.",                                  "stats": { "def": 10,   "hp": 12                  }, "stackable": false },

  { "id": "manto_t2",    "name": "Manto de Seda Tecida",              "emoji": "👘", "type": "armor", "rarity": "common",    "tier": 2,  "description": "Seda refinada tecida com técnicas de artesãos habilidosos.",                             "stats": { "def": 6,    "hp": 53,    "crit": 6    }, "stackable": false },
  { "id": "coura_t2",    "name": "Couraça de Couro Reforçado",        "emoji": "🥋", "type": "armor", "rarity": "common",    "tier": 2,  "description": "Couro reforçado com técnicas tradicionais. Mais resistente.",                             "stats": { "def": 14,   "hp": 20,    "speed": 8   }, "stackable": false },
  { "id": "armadura_t2", "name": "Armadura de Ferro Forjado",         "emoji": "🛡️", "type": "armor", "rarity": "common",    "tier": 2,  "description": "Ferro forjado em placas completas. Defesa superior ao bronze.",                           "stats": { "def": 24,   "hp": 24                  }, "stackable": false },

  { "id": "manto_t3",    "name": "Manto Espiritual de Qi",            "emoji": "👘", "type": "armor", "rarity": "uncommon",  "tier": 3,  "description": "Tecido imbuído de Qi espiritual. Protege corpo e mente.",                                 "stats": { "def": 12,   "hp": 125,   "crit": 12   }, "stackable": false },
  { "id": "coura_t3",    "name": "Couraça Espiritual do Caçador",     "emoji": "🥋", "type": "armor", "rarity": "uncommon",  "tier": 3,  "description": "Couro de besta espiritual tratado com Qi de caçador.",                                   "stats": { "def": 33,   "hp": 40,    "speed": 16  }, "stackable": false },
  { "id": "armadura_t3", "name": "Armadura Espiritual de Aço",        "emoji": "🛡️", "type": "armor", "rarity": "uncommon",  "tier": 3,  "description": "Aço temperado com Qi espiritual. Resistência além do comum.",                            "stats": { "def": 56,   "hp": 48                  }, "stackable": false },

  { "id": "manto_t4",    "name": "Manto Místico do Vazio",            "emoji": "👘", "type": "armor", "rarity": "spiritual", "tier": 4,  "description": "Tecido com energia do vazio místico. Precisão aprimorada.",                              "stats": { "def": 21,   "hp": 238,   "crit": 21   }, "stackable": false },
  { "id": "coura_t4",    "name": "Couraça Mística das Feras",         "emoji": "🥋", "type": "armor", "rarity": "spiritual", "tier": 4,  "description": "Feita de peles de feras místicas. Agilidade e defesa equilibradas.",                      "stats": { "def": 63,   "hp": 70,    "speed": 28  }, "stackable": false },
  { "id": "armadura_t4", "name": "Armadura Mística de Pedra-Ferro",   "emoji": "🛡️", "type": "armor", "rarity": "spiritual", "tier": 4,  "description": "Liga de pedra mística e ferro. Quase impenetrável.",                                     "stats": { "def": 106,  "hp": 84                  }, "stackable": false },

  { "id": "manto_t5",    "name": "Manto do Núcleo Dourado",           "emoji": "👘", "type": "armor", "rarity": "rare",      "tier": 5,  "description": "Luz do Núcleo Dourado tecida em seda celestial.",                                        "stats": { "def": 34,   "hp": 405,   "crit": 34   }, "stackable": false },
  { "id": "coura_t5",    "name": "Couraça do Núcleo Veloz",           "emoji": "🥋", "type": "armor", "rarity": "rare",      "tier": 5,  "description": "Energia do Núcleo impregnada no couro. Velocidade excepcional.",                         "stats": { "def": 107,  "hp": 112,   "speed": 45  }, "stackable": false },
  { "id": "armadura_t5", "name": "Armadura do Núcleo de Ferro",       "emoji": "🛡️", "type": "armor", "rarity": "rare",      "tier": 5,  "description": "Ferro temperado com energia do Núcleo Dourado. Defesa máxima.",                          "stats": { "def": 180,  "hp": 134                 }, "stackable": false },

  { "id": "manto_t6",    "name": "Manto do Espírito Etéreo",          "emoji": "👘", "type": "armor", "rarity": "rare",      "tier": 6,  "description": "Feito de almas etéreas condensadas. Aumenta percepção espiritual.",                      "stats": { "def": 59,   "hp": 757,   "crit": 59   }, "stackable": false },
  { "id": "coura_t6",    "name": "Couraça do Espírito Selvagem",      "emoji": "🥋", "type": "armor", "rarity": "rare",      "tier": 6,  "description": "Espíritos selvagens habitam o couro, conferindo agilidade sobrenatural.",               "stats": { "def": 200,  "hp": 194,   "speed": 78  }, "stackable": false },
  { "id": "armadura_t6", "name": "Armadura do Espírito de Pedra",     "emoji": "🛡️", "type": "armor", "rarity": "rare",      "tier": 6,  "description": "Pedra espiritual forjada em armadura completa. Muralha viva.",                          "stats": { "def": 337,  "hp": 232                 }, "stackable": false },

  { "id": "manto_t7",    "name": "Manto do Rei das Névoas",           "emoji": "👘", "type": "armor", "rarity": "ancient",   "tier": 7,  "description": "Névoa real cristalizada em tecido. Protege como as névoas do reino.",                   "stats": { "def": 104,  "hp": 1438,  "crit": 104  }, "stackable": false },
  { "id": "coura_t7",    "name": "Couraça do Rei das Feras",          "emoji": "🥋", "type": "armor", "rarity": "ancient",   "tier": 7,  "description": "Feita do couro do Rei das Feras. Velocidade digna de realeza.",                         "stats": { "def": 380,  "hp": 343,   "speed": 138 }, "stackable": false },
  { "id": "armadura_t7", "name": "Armadura do Rei de Aço",            "emoji": "🛡️", "type": "armor", "rarity": "ancient",   "tier": 7,  "description": "Forjada para o Rei de Aço. Defesa que subjuga exércitos.",                              "stats": { "def": 640,  "hp": 411                 }, "stackable": false },

  { "id": "manto_t8",    "name": "Manto Imperial das Ilusões",        "emoji": "👘", "type": "armor", "rarity": "ancient",   "tier": 8,  "description": "Ilusões imperiais tecidas em cada fio. Confunde e protege.",                            "stats": { "def": 192,  "hp": 2804,  "crit": 192  }, "stackable": false },
  { "id": "coura_t8",    "name": "Couraça Imperial do Leopardo",      "emoji": "🥋", "type": "armor", "rarity": "ancient",   "tier": 8,  "description": "Pele do Leopardo Imperial. Velocidade e ferocidade imperiais.",                         "stats": { "def": 741,  "hp": 635,   "speed": 255 }, "stackable": false },
  { "id": "armadura_t8", "name": "Armadura Imperial de Jade",         "emoji": "🛡️", "type": "armor", "rarity": "ancient",   "tier": 8,  "description": "Jade imperial fundido em placas. Símbolo do poder imperial.",                          "stats": { "def": 1248, "hp": 760                 }, "stackable": false },

  { "id": "manto_t9",    "name": "Manto Sagrado da Ascensão",         "emoji": "👘", "type": "armor", "rarity": "legendary", "tier": 9,  "description": "Abençoado pelos caminhos sagrados da Ascensão.",                                        "stats": { "def": 422,  "hp": 6730,  "crit": 422  }, "stackable": false },
  { "id": "coura_t9",    "name": "Couraça Sagrada do Vento",          "emoji": "🥋", "type": "armor", "rarity": "legendary", "tier": 9,  "description": "Vento sagrado cristalizado em couro. Move-se como o próprio vento.",                    "stats": { "def": 1778, "hp": 1397,  "speed": 561 }, "stackable": false },
  { "id": "armadura_t9", "name": "Armadura Sagrada do Trovão",        "emoji": "🛡️", "type": "armor", "rarity": "legendary", "tier": 9,  "description": "Trovão sagrado cristalizado em metal. Defesa dos guardiões celestiais.",               "stats": { "def": 2995, "hp": 1672                }, "stackable": false },

  { "id": "manto_t10",    "name": "Manto Divino da Criação",          "emoji": "👘", "type": "armor", "rarity": "legendary", "tier": 10, "description": "Tecido no momento da criação do universo. Proteção absoluta.",                          "stats": { "def": 1182, "hp": 21536, "crit": 1182 }, "stackable": false },
  { "id": "coura_t10",    "name": "Couraça Divina do Dragão",         "emoji": "🥋", "type": "armor", "rarity": "legendary", "tier": 10, "description": "Escamas do Dragão Divino transformadas em couraça. Velocidade absoluta.",               "stats": { "def": 5690, "hp": 3912,  "speed": 1571}, "stackable": false },
  { "id": "armadura_t10", "name": "Armadura Divina do Cataclismo",    "emoji": "🛡️", "type": "armor", "rarity": "legendary", "tier": 10, "description": "Forjada no calor do cataclismo divino. Proteção sem igual no universo.",               "stats": { "def": 9584, "hp": 4682                }, "stackable": false }
]
